splunk_mcp.py
mseep_splunk_mcp-0.3.1.dist-info/LICENSE
mseep_splunk_mcp-0.3.1.dist-info/METADATA
mseep_splunk_mcp-0.3.1.dist-info/NOTICE
mseep_splunk_mcp-0.3.1.dist-info/WHEEL
mseep_splunk_mcp-0.3.1.dist-info/entry_points.txt
mseep_splunk_mcp-0.3.1.dist-info/RECORD
