Metadata-Version: 2.3
Name: mseep-splunk-mcp
Version: 0.3.1
Summary: Splunk MCP (Model Context Protocol) Server for AI Assistants
Author: mseep
Author-email: support@skydeck.ai
Maintainer: mseep
Maintainer-email: support@skydeck.ai
Requires-Python: >=3.10,<4.0
Classifier: Programming Language :: Python :: 3
Classifier: Programming Language :: Python :: 3.10
Classifier: Programming Language :: Python :: 3.11
Classifier: Programming Language :: Python :: 3.12
Classifier: Programming Language :: Python :: 3.13
Requires-Dist: fastmcp (>=0.4.0)
Requires-Dist: python-decouple (>=3.8)
Requires-Dist: requests (>=2.31.0)
Requires-Dist: splunk-sdk (>=1.7.4)
